django_rest_auth/__init__.py
django_rest_auth/admin.py
django_rest_auth/apps.py
django_rest_auth/decorators.py
django_rest_auth/midlleware.py
django_rest_auth/models.py
django_rest_auth/serializers.py
django_rest_auth/sidebar.py
django_rest_auth/urls.py
django_rest_auth/views.py
django_rest_auth/viewsApi.py
django_rest_auth/classes/FullPath.py
django_rest_auth/classes/Translate.py
django_rest_auth/classes/Translation.py
django_rest_auth/classes/UserName.py
django_rest_auth/migrations/0001_initial.py
django_rest_auth/migrations/__init__.py
django_rest_auth/templates/email_confirmacao.html
django_rest_auth/templates/email_reset.html
mytech_rest_auth-1.1.5.dist-info/licenses/LICENSE
mytech_rest_auth-1.1.5.dist-info/METADATA
mytech_rest_auth-1.1.5.dist-info/WHEEL
mytech_rest_auth-1.1.5.dist-info/top_level.txt
mytech_rest_auth-1.1.5.dist-info/RECORD
