Metadata-Version: 2.4
Name: mytech_rest_auth
Version: 1.1.5
Summary: App de autenticação e gestão de entidades para Django REST Framework
Author-email: Dias Metano Salvador Chavana <metanochava@gmail.com>
License: MIT License
Project-URL: Homepage, https://github.com/metanochava/django_rest_auth
Project-URL: Repository, https://github.com/metanochava/django_rest_auth
Requires-Python: >=3.9
License-File: LICENSE
Dynamic: license-file
